revpayment/__init__.py
revpayment/actions.py
revpayment/calculations.py
revpayment/carts.py
revpayment/checkout.py
revpayment/config.py
revpayment/exceptions.py
revpayment/handlers.py
revpayment/items.py
revpayment/models.py
revpayment/payments.py
revpayment/settings.py
revpayment/urls.py
revpayment/views.py
revpayment/invoice/__init__.py
revpayment/invoice/actions.py
revpayment/invoice/apps.py
revpayment/invoice/exceptions.py
revpayment/invoice/models.py
revpayment/invoice/providers.py
revpayment/invoice/migrations/0001_initial.py
revpayment/invoice/migrations/__init__.py
revpayment/logistics/__init__.py
revpayment/logistics/admin.py
revpayment/logistics/apps.py
revpayment/logistics/models.py
revpayment/logistics/providers.py
revpayment/logistics/tests.py
revpayment/logistics/views.py
revpayment/logistics/migrations/0001_initial.py
revpayment/logistics/migrations/__init__.py
revpayment/migrations/0001_initial.py
revpayment/migrations/0002_order_pay_deadline.py
revpayment/migrations/0003_paymentinfo_uid.py
revpayment/migrations/__init__.py
revpayment/utils/__init__.py
revpayment-3.1.3.dist-info/METADATA
revpayment-3.1.3.dist-info/WHEEL
revpayment-3.1.3.dist-info/top_level.txt
revpayment-3.1.3.dist-info/RECORD
