Metadata-Version: 2.1
Name: revpayment
Version: 3.1.3
Summary: payment service for revteltech
Home-page: https://github.com/revtel/revpayment
Author: Chien Hsiao
Author-email: chien.hsiao@revteltech.com
License: MIT
Keywords: revteltech,payment
Platform: UNKNOWN
Classifier: Development Status :: 3 - Alpha
Classifier: Intended Audience :: Developers
Classifier: Topic :: Software Development :: Build Tools
Classifier: License :: OSI Approved :: MIT License
Classifier: Programming Language :: Python :: 3
Classifier: Programming Language :: Python :: 3.6
Classifier: Programming Language :: Python :: 3.7
Requires-Dist: django
Requires-Dist: djangorestframework
Requires-Dist: requests
Requires-Dist: revjwt
